MANIFEST.in
README.md
setup.py
tests/__init__.py
tests/test_packaging.py
tests/end2end/__init__.py
tests/end2end/test_model_admin.py
tests/end2end/test_model_polymorphic.py
tests/end2end/test_model_simple.py
tests/end2end/test_page_simple.py
tests/unit/__init__.py
tests/unit/test_bugs.py
tests/unit/test_celery.py
tests/unit/test_channels.py
tests/unit/test_docker.py
tests/unit/test_files.py
tests/unit/test_gitlab.py
tests/unit/test_imports.py
tests/unit/test_requirements.py
tests/unit/test_suit.py
tests/unit/test_theme.py
tests/unit/test_utils.py
tests/unit/fields/__init__.py
tests/unit/fields/test_bool.py
tests/unit/fields/test_calculated.py
tests/unit/fields/test_date.py
tests/unit/fields/test_file.py
tests/unit/fields/test_number.py
tests/unit/fields/test_rel.py
tests/unit/fields/test_slug.py
tests/unit/fields/test_text.py
tests/unit/model/__init__.py
tests/unit/model/test_admin_class.py
tests/unit/model/test_clean.py
tests/unit/model/test_date_tree.py
tests/unit/model/test_db_handlers.py
tests/unit/model/test_field_extend.py
tests/unit/model/test_mixin.py
tests/unit/model/test_populate_admin.py
tests/unit/model/test_populate_model.py
tests/unit/model/test_populate_rest.py
tests/unit/model/test_sortable.py
tests/unit/model/test_tree.py
tests/unit/page/__init__.py
tests/unit/page/test_auth.py
tests/unit/page/test_bases.py
tests/unit/page/test_crud.py
tests/unit/page/test_error.py
tests/unit/page/test_get.py
tests/unit/page/test_html.py
tests/unit/page/test_markdown.py
tests/unit/page/test_menu.py
tests/unit/page/test_page_expr.py
tests/unit/page/test_populate_page.py
tests/unit/page/test_post.py
tests/unit/page/test_priority.py
tests/unit/page/test_react.py
tests/unit/page/test_stream.py
tests/unit/project/__init__.py
tests/unit/project/test_crud.py
tests/unit/project/test_menu.py
tests/unit/project/test_pages.py
tests/unit/project/test_populate_rest.py
tests/unit/project/test_rel.py
tests/unit/project/test_stream.py
zmei_cli.egg-info/PKG-INFO
zmei_cli.egg-info/SOURCES.txt
zmei_cli.egg-info/dependency_links.txt
zmei_cli.egg-info/entry_points.txt
zmei_cli.egg-info/requires.txt
zmei_cli.egg-info/top_level.txt
zmei_generator/__init__.py
