Metadata-Version: 1.0
Name: zmei-cli
Version: 2.1.10
Summary: Zmei-generator
Home-page: UNKNOWN
Author: Alex Rudakov
Author-email: ribozz@gmail.com
License: GPLv3
Platform: UNKNOWN
